[
  {
    "name": "The Shrine",
    "description": "A gleaming building dedicated to the divine spirit",
    "spaces": [
      {
        "name": "Main Hall",
        "width": 20,
        "height": 20,
        "entry_col": 0,
        "entry_row": 0,
        "tiles": {
          "0,0": {
            "tile_id": 1,
            "name": "Water"
          },
          "1,0": {
            "tile_id": 1,
            "name": "Water"
          },
          "2,0": {
            "tile_id": 1,
            "name": "Water"
          },
          "3,0": {
            "tile_id": 1,
            "name": "Water"
          },
          "4,0": {
            "tile_id": 1,
            "name": "Water"
          },
          "5,0": {
            "tile_id": 1,
            "name": "Water"
          },
          "6,0": {
            "tile_id": 1,
            "name": "Water"
          },
          "7,0": {
            "tile_id": 1,
            "name": "Water"
          },
          "8,0": {
            "tile_id": 1,
            "name": "Water"
          },
          "9,0": {
            "tile_id": 1,
            "name": "Water"
          },
          "10,0": {
            "tile_id": 1,
            "name": "Water"
          },
          "11,0": {
            "tile_id": 1,
            "name": "Water"
          },
          "12,0": {
            "tile_id": 1,
            "name": "Water"
          },
          "13,0": {
            "tile_id": 1,
            "name": "Water"
          },
          "14,0": {
            "tile_id": 1,
            "name": "Water"
          },
          "15,0": {
            "tile_id": 1,
            "name": "Water"
          },
          "16,0": {
            "tile_id": 1,
            "name": "Water"
          },
          "17,0": {
            "tile_id": 1,
            "name": "Water"
          },
          "18,0": {
            "tile_id": 1,
            "name": "Water"
          },
          "19,0": {
            "tile_id": 1,
            "name": "Water"
          },
          "0,1": {
            "tile_id": 1,
            "name": "Water"
          },
          "1,1": {
            "tile_id": 1,
            "name": "Water"
          },
          "2,1": {
            "tile_id": 1,
            "name": "Water"
          },
          "3,1": {
            "tile_id": 1,
            "name": "Water"
          },
          "4,1": {
            "tile_id": 1,
            "name": "Water"
          },
          "5,1": {
            "tile_id": 1,
            "name": "Water"
          },
          "6,1": {
            "tile_id": 1,
            "name": "Water"
          },
          "7,1": {
            "tile_id": 1,
            "name": "Water"
          },
          "8,1": {
            "tile_id": 1,
            "name": "Water"
          },
          "9,1": {
            "tile_id": 1,
            "name": "Water"
          },
          "10,1": {
            "tile_id": 1,
            "name": "Water"
          },
          "11,1": {
            "tile_id": 1,
            "name": "Water"
          },
          "12,1": {
            "tile_id": 1,
            "name": "Water"
          },
          "13,1": {
            "tile_id": 1,
            "name": "Water"
          },
          "14,1": {
            "tile_id": 1,
            "name": "Water"
          },
          "15,1": {
            "tile_id": 1,
            "name": "Water"
          },
          "16,1": {
            "tile_id": 1,
            "name": "Water"
          },
          "17,1": {
            "tile_id": 1,
            "name": "Water"
          },
          "18,1": {
            "tile_id": 1,
            "name": "Water"
          },
          "19,1": {
            "tile_id": 1,
            "name": "Water"
          },
          "0,2": {
            "tile_id": 1,
            "name": "Water"
          },
          "1,2": {
            "tile_id": 1,
            "name": "Water"
          },
          "2,2": {
            "tile_id": 1,
            "name": "Water"
          },
          "3,2": {
            "tile_id": 1,
            "name": "Water"
          },
          "4,2": {
            "tile_id": 1,
            "name": "Water"
          },
          "5,2": {
            "tile_id": 1,
            "name": "Water"
          },
          "6,2": {
            "tile_id": 1,
            "name": "Water"
          },
          "7,2": {
            "tile_id": 1,
            "name": "Water"
          },
          "8,2": {
            "tile_id": 1,
            "name": "Water"
          },
          "9,2": {
            "tile_id": 1,
            "name": "Water"
          },
          "10,2": {
            "tile_id": 1,
            "name": "Water"
          },
          "11,2": {
            "tile_id": 1,
            "name": "Water"
          },
          "12,2": {
            "tile_id": 1,
            "name": "Water"
          },
          "13,2": {
            "tile_id": 1,
            "name": "Water"
          },
          "14,2": {
            "tile_id": 1,
            "name": "Water"
          },
          "15,2": {
            "tile_id": 1,
            "name": "Water"
          },
          "16,2": {
            "tile_id": 1,
            "name": "Water"
          },
          "17,2": {
            "tile_id": 1,
            "name": "Water"
          },
          "18,2": {
            "tile_id": 1,
            "name": "Water"
          },
          "19,2": {
            "tile_id": 1,
            "name": "Water"
          },
          "0,3": {
            "tile_id": 1,
            "name": "Water"
          },
          "1,3": {
            "tile_id": 1,
            "name": "Water"
          },
          "2,3": {
            "tile_id": 1,
            "name": "Water"
          },
          "3,3": {
            "tile_id": 1,
            "name": "Water"
          },
          "4,3": {
            "tile_id": 1,
            "name": "Water"
          },
          "5,3": {
            "tile_id": 1,
            "name": "Water"
          },
          "6,3": {
            "tile_id": 1,
            "name": "Water"
          },
          "7,3": {
            "tile_id": 1,
            "name": "Water"
          },
          "8,3": {
            "tile_id": 1,
            "name": "Water"
          },
          "9,3": {
            "tile_id": 1,
            "name": "Water"
          },
          "10,3": {
            "tile_id": 1,
            "name": "Water"
          },
          "11,3": {
            "tile_id": 1,
            "name": "Water"
          },
          "12,3": {
            "tile_id": 1,
            "name": "Water"
          },
          "13,3": {
            "tile_id": 1,
            "name": "Water"
          },
          "14,3": {
            "tile_id": 1,
            "name": "Water"
          },
          "15,3": {
            "tile_id": 1,
            "name": "Water"
          },
          "16,3": {
            "tile_id": 1,
            "name": "Water"
          },
          "17,3": {
            "tile_id": 1,
            "name": "Water"
          },
          "18,3": {
            "tile_id": 1,
            "name": "Water"
          },
          "19,3": {
            "tile_id": 1,
            "name": "Water"
          },
          "0,4": {
            "tile_id": 1,
            "name": "Water"
          },
          "1,4": {
            "tile_id": 1,
            "name": "Water"
          },
          "2,4": {
            "tile_id": 1,
            "name": "Water"
          },
          "3,4": {
            "tile_id": 1,
            "name": "Water"
          },
          "4,4": {
            "tile_id": 1,
            "name": "Water"
          },
          "5,4": {
            "tile_id": 1,
            "name": "Water"
          },
          "6,4": {
            "tile_id": 1,
            "name": "Water"
          },
          "7,4": {
            "tile_id": 1,
            "name": "Water"
          },
          "8,4": {
            "tile_id": 1,
            "name": "Water"
          },
          "9,4": {
            "tile_id": 1,
            "name": "Water"
          },
          "10,4": {
            "tile_id": 1,
            "name": "Water"
          },
          "11,4": {
            "tile_id": 1,
            "name": "Water"
          },
          "12,4": {
            "tile_id": 1,
            "name": "Water"
          },
          "13,4": {
            "tile_id": 1,
            "name": "Water"
          },
          "14,4": {
            "tile_id": 1,
            "name": "Water"
          },
          "15,4": {
            "tile_id": 1,
            "name": "Water"
          },
          "16,4": {
            "tile_id": 1,
            "name": "Water"
          },
          "17,4": {
            "tile_id": 1,
            "name": "Water"
          },
          "18,4": {
            "tile_id": 1,
            "name": "Water"
          },
          "19,4": {
            "tile_id": 1,
            "name": "Water"
          },
          "0,5": {
            "tile_id": 1,
            "name": "Water"
          },
          "1,5": {
            "tile_id": 1,
            "name": "Water"
          },
          "2,5": {
            "tile_id": 1,
            "name": "Water"
          },
          "3,5": {
            "tile_id": 1,
            "name": "Water"
          },
          "4,5": {
            "tile_id": 1,
            "name": "Water"
          },
          "5,5": {
            "tile_id": 1,
            "name": "Water"
          },
          "6,5": {
            "tile_id": 1,
            "name": "Water"
          },
          "7,5": {
            "tile_id": 1,
            "name": "Water"
          },
          "8,5": {
            "tile_id": 1,
            "name": "Water"
          },
          "9,5": {
            "tile_id": 1,
            "name": "Water"
          },
          "10,5": {
            "tile_id": 1,
            "name": "Water"
          },
          "11,5": {
            "tile_id": 1,
            "name": "Water"
          },
          "12,5": {
            "tile_id": 1,
            "name": "Water"
          },
          "13,5": {
            "tile_id": 1,
            "name": "Water"
          },
          "14,5": {
            "tile_id": 1,
            "name": "Water"
          },
          "15,5": {
            "tile_id": 1,
            "name": "Water"
          },
          "16,5": {
            "tile_id": 1,
            "name": "Water"
          },
          "17,5": {
            "tile_id": 1,
            "name": "Water"
          },
          "18,5": {
            "tile_id": 1,
            "name": "Water"
          },
          "19,5": {
            "tile_id": 1,
            "name": "Water"
          },
          "0,6": {
            "tile_id": 1,
            "name": "Water"
          },
          "1,6": {
            "tile_id": 1,
            "name": "Water"
          },
          "2,6": {
            "tile_id": 21,
            "name": "Stone Wall"
          },
          "3,6": {
            "tile_id": 21,
            "name": "Stone Wall"
          },
          "4,6": {
            "tile_id": 21,
            "name": "Stone Wall"
          },
          "5,6": {
            "tile_id": 21,
            "name": "Stone Wall"
          },
          "6,6": {
            "tile_id": 21,
            "name": "Stone Wall"
          },
          "7,6": {
            "tile_id": 21,
            "name": "Stone Wall"
          },
          "8,6": {
            "tile_id": 21,
            "name": "Stone Wall"
          },
          "9,6": {
            "tile_id": 21,
            "name": "Stone Wall"
          },
          "10,6": {
            "tile_id": 21,
            "name": "Stone Wall"
          },
          "11,6": {
            "tile_id": 21,
            "name": "Stone Wall"
          },
          "12,6": {
            "tile_id": 21,
            "name": "Stone Wall"
          },
          "13,6": {
            "tile_id": 21,
            "name": "Stone Wall"
          },
          "14,6": {
            "tile_id": 21,
            "name": "Stone Wall"
          },
          "15,6": {
            "tile_id": 21,
            "name": "Stone Wall"
          },
          "16,6": {
            "tile_id": 21,
            "name": "Stone Wall"
          },
          "17,6": {
            "tile_id": 21,
            "name": "Stone Wall"
          },
          "18,6": {
            "tile_id": 1,
            "name": "Water"
          },
          "19,6": {
            "tile_id": 1,
            "name": "Water"
          },
          "0,7": {
            "tile_id": 1,
            "name": "Water"
          },
          "1,7": {
            "tile_id": 1,
            "name": "Water"
          },
          "2,7": {
            "tile_id": 21,
            "name": "Stone Wall"
          },
          "3,7": {
            "tile_id": 35,
            "name": "Altar"
          },
          "4,7": {
            "tile_id": 7,
            "name": "Sand"
          },
          "5,7": {
            "tile_id": 7,
            "name": "Sand"
          },
          "6,7": {
            "tile_id": 7,
            "name": "Sand"
          },
          "7,7": {
            "tile_id": 7,
            "name": "Sand"
          },
          "8,7": {
            "tile_id": 7,
            "name": "Sand"
          },
          "9,7": {
            "tile_id": 7,
            "name": "Sand"
          },
          "10,7": {
            "tile_id": 7,
            "name": "Sand"
          },
          "11,7": {
            "tile_id": 7,
            "name": "Sand"
          },
          "12,7": {
            "tile_id": 7,
            "name": "Sand"
          },
          "13,7": {
            "tile_id": 7,
            "name": "Sand"
          },
          "14,7": {
            "tile_id": 7,
            "name": "Sand"
          },
          "15,7": {
            "tile_id": 7,
            "name": "Sand"
          },
          "16,7": {
            "tile_id": 35,
            "name": "Altar"
          },
          "17,7": {
            "tile_id": 21,
            "name": "Stone Wall"
          },
          "18,7": {
            "tile_id": 1,
            "name": "Water"
          },
          "19,7": {
            "tile_id": 1,
            "name": "Water"
          },
          "0,8": {
            "tile_id": 1,
            "name": "Water"
          },
          "1,8": {
            "tile_id": 1,
            "name": "Water"
          },
          "2,8": {
            "tile_id": 21,
            "name": "Stone Wall"
          },
          "3,8": {
            "tile_id": 7,
            "name": "Sand"
          },
          "4,8": {
            "tile_id": 7,
            "name": "Sand"
          },
          "5,8": {
            "tile_id": 7,
            "name": "Sand"
          },
          "6,8": {
            "tile_id": 7,
            "name": "Sand"
          },
          "7,8": {
            "tile_id": 7,
            "name": "Sand"
          },
          "8,8": {
            "tile_id": 7,
            "name": "Sand"
          },
          "9,8": {
            "tile_id": 7,
            "name": "Sand"
          },
          "10,8": {
            "tile_id": 7,
            "name": "Sand"
          },
          "11,8": {
            "tile_id": 7,
            "name": "Sand"
          },
          "12,8": {
            "tile_id": 7,
            "name": "Sand"
          },
          "13,8": {
            "tile_id": 7,
            "name": "Sand"
          },
          "14,8": {
            "tile_id": 7,
            "name": "Sand"
          },
          "15,8": {
            "tile_id": 7,
            "name": "Sand"
          },
          "16,8": {
            "tile_id": 7,
            "name": "Sand"
          },
          "17,8": {
            "tile_id": 21,
            "name": "Stone Wall"
          },
          "18,8": {
            "tile_id": 1,
            "name": "Water"
          },
          "19,8": {
            "tile_id": 1,
            "name": "Water"
          },
          "0,9": {
            "tile_id": 1,
            "name": "Water"
          },
          "1,9": {
            "tile_id": 1,
            "name": "Water"
          },
          "2,9": {
            "tile_id": 21,
            "name": "Stone Wall"
          },
          "3,9": {
            "tile_id": 7,
            "name": "Sand"
          },
          "4,9": {
            "tile_id": 7,
            "name": "Sand"
          },
          "5,9": {
            "tile_id": 7,
            "name": "Sand"
          },
          "6,9": {
            "tile_id": 7,
            "name": "Sand"
          },
          "7,9": {
            "tile_id": 7,
            "name": "Sand"
          },
          "8,9": {
            "tile_id": 7,
            "name": "Sand"
          },
          "9,9": {
            "tile_id": 7,
            "name": "Sand"
          },
          "10,9": {
            "tile_id": 7,
            "name": "Sand"
          },
          "11,9": {
            "tile_id": 7,
            "name": "Sand"
          },
          "12,9": {
            "tile_id": 7,
            "name": "Sand"
          },
          "13,9": {
            "tile_id": 7,
            "name": "Sand"
          },
          "14,9": {
            "tile_id": 7,
            "name": "Sand"
          },
          "15,9": {
            "tile_id": 7,
            "name": "Sand"
          },
          "16,9": {
            "tile_id": 7,
            "name": "Sand"
          },
          "17,9": {
            "tile_id": 21,
            "name": "Stone Wall"
          },
          "18,9": {
            "tile_id": 1,
            "name": "Water"
          },
          "19,9": {
            "tile_id": 1,
            "name": "Water"
          },
          "0,10": {
            "tile_id": 1,
            "name": "Water"
          },
          "1,10": {
            "tile_id": 1,
            "name": "Water"
          },
          "2,10": {
            "tile_id": 21,
            "name": "Stone Wall"
          },
          "3,10": {
            "tile_id": 7,
            "name": "Sand"
          },
          "4,10": {
            "tile_id": 7,
            "name": "Sand"
          },
          "5,10": {
            "tile_id": 7,
            "name": "Sand"
          },
          "6,10": {
            "tile_id": 7,
            "name": "Sand"
          },
          "7,10": {
            "tile_id": 7,
            "name": "Sand"
          },
          "8,10": {
            "tile_id": 7,
            "name": "Sand"
          },
          "9,10": {
            "tile_id": 7,
            "name": "Sand"
          },
          "10,10": {
            "tile_id": 7,
            "name": "Sand"
          },
          "11,10": {
            "tile_id": 7,
            "name": "Sand"
          },
          "12,10": {
            "tile_id": 7,
            "name": "Sand"
          },
          "13,10": {
            "tile_id": 7,
            "name": "Sand"
          },
          "14,10": {
            "tile_id": 7,
            "name": "Sand"
          },
          "15,10": {
            "tile_id": 7,
            "name": "Sand"
          },
          "16,10": {
            "tile_id": 7,
            "name": "Sand"
          },
          "17,10": {
            "tile_id": 21,
            "name": "Stone Wall"
          },
          "18,10": {
            "tile_id": 1,
            "name": "Water"
          },
          "19,10": {
            "tile_id": 1,
            "name": "Water"
          },
          "0,11": {
            "tile_id": 1,
            "name": "Water"
          },
          "1,11": {
            "tile_id": 1,
            "name": "Water"
          },
          "2,11": {
            "tile_id": 21,
            "name": "Stone Wall"
          },
          "3,11": {
            "tile_id": 7,
            "name": "Sand"
          },
          "4,11": {
            "tile_id": 7,
            "name": "Sand"
          },
          "5,11": {
            "tile_id": 7,
            "name": "Sand"
          },
          "6,11": {
            "tile_id": 7,
            "name": "Sand"
          },
          "7,11": {
            "tile_id": 7,
            "name": "Sand"
          },
          "8,11": {
            "tile_id": 7,
            "name": "Sand"
          },
          "9,11": {
            "tile_id": 7,
            "name": "Sand"
          },
          "10,11": {
            "tile_id": 7,
            "name": "Sand"
          },
          "11,11": {
            "tile_id": 7,
            "name": "Sand"
          },
          "12,11": {
            "tile_id": 7,
            "name": "Sand"
          },
          "13,11": {
            "tile_id": 7,
            "name": "Sand"
          },
          "14,11": {
            "tile_id": 7,
            "name": "Sand"
          },
          "15,11": {
            "tile_id": 7,
            "name": "Sand"
          },
          "16,11": {
            "tile_id": 7,
            "name": "Sand"
          },
          "17,11": {
            "tile_id": 21,
            "name": "Stone Wall"
          },
          "18,11": {
            "tile_id": 1,
            "name": "Water"
          },
          "19,11": {
            "tile_id": 1,
            "name": "Water"
          },
          "0,12": {
            "tile_id": 1,
            "name": "Water"
          },
          "1,12": {
            "tile_id": 1,
            "name": "Water"
          },
          "2,12": {
            "tile_id": 21,
            "name": "Stone Wall"
          },
          "3,12": {
            "tile_id": 7,
            "name": "Sand"
          },
          "4,12": {
            "tile_id": 7,
            "name": "Sand"
          },
          "5,12": {
            "tile_id": 7,
            "name": "Sand"
          },
          "6,12": {
            "tile_id": 7,
            "name": "Sand"
          },
          "7,12": {
            "tile_id": 7,
            "name": "Sand"
          },
          "8,12": {
            "tile_id": 7,
            "name": "Sand"
          },
          "9,12": {
            "tile_id": 13,
            "name": "Door",
            "to_overworld": true
          },
          "10,12": {
            "tile_id": 7,
            "name": "Sand"
          },
          "11,12": {
            "tile_id": 7,
            "name": "Sand"
          },
          "12,12": {
            "tile_id": 7,
            "name": "Sand"
          },
          "13,12": {
            "tile_id": 7,
            "name": "Sand"
          },
          "14,12": {
            "tile_id": 7,
            "name": "Sand"
          },
          "15,12": {
            "tile_id": 7,
            "name": "Sand"
          },
          "16,12": {
            "tile_id": 7,
            "name": "Sand"
          },
          "17,12": {
            "tile_id": 21,
            "name": "Stone Wall"
          },
          "18,12": {
            "tile_id": 1,
            "name": "Water"
          },
          "19,12": {
            "tile_id": 1,
            "name": "Water"
          },
          "0,13": {
            "tile_id": 1,
            "name": "Water"
          },
          "1,13": {
            "tile_id": 1,
            "name": "Water"
          },
          "2,13": {
            "tile_id": 21,
            "name": "Stone Wall"
          },
          "3,13": {
            "tile_id": 7,
            "name": "Sand"
          },
          "4,13": {
            "tile_id": 7,
            "name": "Sand"
          },
          "5,13": {
            "tile_id": 7,
            "name": "Sand"
          },
          "6,13": {
            "tile_id": 7,
            "name": "Sand"
          },
          "7,13": {
            "tile_id": 7,
            "name": "Sand"
          },
          "8,13": {
            "tile_id": 7,
            "name": "Sand"
          },
          "9,13": {
            "tile_id": 7,
            "name": "Sand"
          },
          "10,13": {
            "tile_id": 7,
            "name": "Sand"
          },
          "11,13": {
            "tile_id": 7,
            "name": "Sand"
          },
          "12,13": {
            "tile_id": 7,
            "name": "Sand"
          },
          "13,13": {
            "tile_id": 7,
            "name": "Sand"
          },
          "14,13": {
            "tile_id": 7,
            "name": "Sand"
          },
          "15,13": {
            "tile_id": 7,
            "name": "Sand"
          },
          "16,13": {
            "tile_id": 7,
            "name": "Sand"
          },
          "17,13": {
            "tile_id": 21,
            "name": "Stone Wall"
          },
          "18,13": {
            "tile_id": 1,
            "name": "Water"
          },
          "19,13": {
            "tile_id": 1,
            "name": "Water"
          },
          "0,14": {
            "tile_id": 1,
            "name": "Water"
          },
          "1,14": {
            "tile_id": 1,
            "name": "Water"
          },
          "2,14": {
            "tile_id": 21,
            "name": "Stone Wall"
          },
          "3,14": {
            "tile_id": 21,
            "name": "Stone Wall"
          },
          "4,14": {
            "tile_id": 7,
            "name": "Sand"
          },
          "5,14": {
            "tile_id": 7,
            "name": "Sand"
          },
          "6,14": {
            "tile_id": 7,
            "name": "Sand"
          },
          "7,14": {
            "tile_id": 7,
            "name": "Sand"
          },
          "8,14": {
            "tile_id": 7,
            "name": "Sand"
          },
          "9,14": {
            "tile_id": 7,
            "name": "Sand"
          },
          "10,14": {
            "tile_id": 7,
            "name": "Sand"
          },
          "11,14": {
            "tile_id": 7,
            "name": "Sand"
          },
          "12,14": {
            "tile_id": 7,
            "name": "Sand"
          },
          "13,14": {
            "tile_id": 7,
            "name": "Sand"
          },
          "14,14": {
            "tile_id": 7,
            "name": "Sand"
          },
          "15,14": {
            "tile_id": 7,
            "name": "Sand"
          },
          "16,14": {
            "tile_id": 21,
            "name": "Stone Wall"
          },
          "17,14": {
            "tile_id": 21,
            "name": "Stone Wall"
          },
          "18,14": {
            "tile_id": 1,
            "name": "Water"
          },
          "19,14": {
            "tile_id": 1,
            "name": "Water"
          },
          "0,15": {
            "tile_id": 1,
            "name": "Water"
          },
          "1,15": {
            "tile_id": 1,
            "name": "Water"
          },
          "2,15": {
            "tile_id": 1,
            "name": "Water"
          },
          "3,15": {
            "tile_id": 21,
            "name": "Stone Wall"
          },
          "4,15": {
            "tile_id": 21,
            "name": "Stone Wall"
          },
          "5,15": {
            "tile_id": 7,
            "name": "Sand"
          },
          "6,15": {
            "tile_id": 7,
            "name": "Sand"
          },
          "7,15": {
            "tile_id": 7,
            "name": "Sand"
          },
          "8,15": {
            "tile_id": 7,
            "name": "Sand"
          },
          "9,15": {
            "tile_id": 7,
            "name": "Sand"
          },
          "10,15": {
            "tile_id": 7,
            "name": "Sand"
          },
          "11,15": {
            "tile_id": 7,
            "name": "Sand"
          },
          "12,15": {
            "tile_id": 7,
            "name": "Sand"
          },
          "13,15": {
            "tile_id": 7,
            "name": "Sand"
          },
          "14,15": {
            "tile_id": 7,
            "name": "Sand"
          },
          "15,15": {
            "tile_id": 21,
            "name": "Stone Wall"
          },
          "16,15": {
            "tile_id": 21,
            "name": "Stone Wall"
          },
          "17,15": {
            "tile_id": 1,
            "name": "Water"
          },
          "18,15": {
            "tile_id": 1,
            "name": "Water"
          },
          "19,15": {
            "tile_id": 1,
            "name": "Water"
          },
          "0,16": {
            "tile_id": 1,
            "name": "Water"
          },
          "1,16": {
            "tile_id": 1,
            "name": "Water"
          },
          "2,16": {
            "tile_id": 1,
            "name": "Water"
          },
          "3,16": {
            "tile_id": 1,
            "name": "Water"
          },
          "4,16": {
            "tile_id": 21,
            "name": "Stone Wall"
          },
          "5,16": {
            "tile_id": 7,
            "name": "Sand"
          },
          "6,16": {
            "tile_id": 7,
            "name": "Sand"
          },
          "7,16": {
            "tile_id": 7,
            "name": "Sand"
          },
          "8,16": {
            "tile_id": 7,
            "name": "Sand"
          },
          "9,16": {
            "tile_id": 7,
            "name": "Sand"
          },
          "10,16": {
            "tile_id": 7,
            "name": "Sand"
          },
          "11,16": {
            "tile_id": 7,
            "name": "Sand"
          },
          "12,16": {
            "tile_id": 7,
            "name": "Sand"
          },
          "13,16": {
            "tile_id": 7,
            "name": "Sand"
          },
          "14,16": {
            "tile_id": 21,
            "name": "Stone Wall"
          },
          "15,16": {
            "tile_id": 21,
            "name": "Stone Wall"
          },
          "16,16": {
            "tile_id": 1,
            "name": "Water"
          },
          "17,16": {
            "tile_id": 1,
            "name": "Water"
          },
          "18,16": {
            "tile_id": 1,
            "name": "Water"
          },
          "19,16": {
            "tile_id": 1,
            "name": "Water"
          },
          "0,17": {
            "tile_id": 1,
            "name": "Water"
          },
          "1,17": {
            "tile_id": 1,
            "name": "Water"
          },
          "2,17": {
            "tile_id": 1,
            "name": "Water"
          },
          "3,17": {
            "tile_id": 1,
            "name": "Water"
          },
          "4,17": {
            "tile_id": 21,
            "name": "Stone Wall"
          },
          "5,17": {
            "tile_id": 21,
            "name": "Stone Wall"
          },
          "6,17": {
            "tile_id": 7,
            "name": "Sand"
          },
          "7,17": {
            "tile_id": 7,
            "name": "Sand"
          },
          "8,17": {
            "tile_id": 7,
            "name": "Sand"
          },
          "9,17": {
            "tile_id": 7,
            "name": "Sand"
          },
          "10,17": {
            "tile_id": 7,
            "name": "Sand"
          },
          "11,17": {
            "tile_id": 7,
            "name": "Sand"
          },
          "12,17": {
            "tile_id": 7,
            "name": "Sand"
          },
          "13,17": {
            "tile_id": 21,
            "name": "Stone Wall"
          },
          "14,17": {
            "tile_id": 21,
            "name": "Stone Wall"
          },
          "15,17": {
            "tile_id": 1,
            "name": "Water"
          },
          "16,17": {
            "tile_id": 1,
            "name": "Water"
          },
          "17,17": {
            "tile_id": 1,
            "name": "Water"
          },
          "18,17": {
            "tile_id": 1,
            "name": "Water"
          },
          "19,17": {
            "tile_id": 1,
            "name": "Water"
          },
          "0,18": {
            "tile_id": 1,
            "name": "Water"
          },
          "1,18": {
            "tile_id": 1,
            "name": "Water"
          },
          "2,18": {
            "tile_id": 1,
            "name": "Water"
          },
          "3,18": {
            "tile_id": 1,
            "name": "Water"
          },
          "4,18": {
            "tile_id": 1,
            "name": "Water"
          },
          "5,18": {
            "tile_id": 21,
            "name": "Stone Wall"
          },
          "6,18": {
            "tile_id": 21,
            "name": "Stone Wall"
          },
          "7,18": {
            "tile_id": 7,
            "name": "Sand"
          },
          "8,18": {
            "tile_id": 7,
            "name": "Sand"
          },
          "9,18": {
            "tile_id": 7,
            "name": "Sand"
          },
          "10,18": {
            "tile_id": 7,
            "name": "Sand"
          },
          "11,18": {
            "tile_id": 7,
            "name": "Sand"
          },
          "12,18": {
            "tile_id": 21,
            "name": "Stone Wall"
          },
          "13,18": {
            "tile_id": 21,
            "name": "Stone Wall"
          },
          "14,18": {
            "tile_id": 1,
            "name": "Water"
          },
          "15,18": {
            "tile_id": 1,
            "name": "Water"
          },
          "16,18": {
            "tile_id": 1,
            "name": "Water"
          },
          "17,18": {
            "tile_id": 1,
            "name": "Water"
          },
          "18,18": {
            "tile_id": 1,
            "name": "Water"
          },
          "19,18": {
            "tile_id": 1,
            "name": "Water"
          },
          "0,19": {
            "tile_id": 1,
            "name": "Water"
          },
          "1,19": {
            "tile_id": 1,
            "name": "Water"
          },
          "2,19": {
            "tile_id": 1,
            "name": "Water"
          },
          "3,19": {
            "tile_id": 1,
            "name": "Water"
          },
          "4,19": {
            "tile_id": 1,
            "name": "Water"
          },
          "5,19": {
            "tile_id": 1,
            "name": "Water"
          },
          "6,19": {
            "tile_id": 21,
            "name": "Stone Wall"
          },
          "7,19": {
            "tile_id": 21,
            "name": "Stone Wall"
          },
          "8,19": {
            "tile_id": 21,
            "name": "Stone Wall"
          },
          "9,19": {
            "tile_id": 21,
            "name": "Stone Wall"
          },
          "10,19": {
            "tile_id": 21,
            "name": "Stone Wall"
          },
          "11,19": {
            "tile_id": 21,
            "name": "Stone Wall"
          },
          "12,19": {
            "tile_id": 21,
            "name": "Stone Wall"
          },
          "13,19": {
            "tile_id": 1,
            "name": "Water"
          },
          "14,19": {
            "tile_id": 1,
            "name": "Water"
          },
          "15,19": {
            "tile_id": 1,
            "name": "Water"
          },
          "16,19": {
            "tile_id": 1,
            "name": "Water"
          },
          "17,19": {
            "tile_id": 1,
            "name": "Water"
          },
          "18,19": {
            "tile_id": 1,
            "name": "Water"
          },
          "19,19": {
            "tile_id": 1,
            "name": "Water"
          }
        },
        "encounters": []
      }
    ]
  }
]